LICENSE
MANIFEST.in
README.rst
setup.py
Django_Sites_Templatetags.egg-info/PKG-INFO
Django_Sites_Templatetags.egg-info/SOURCES.txt
Django_Sites_Templatetags.egg-info/dependency_links.txt
Django_Sites_Templatetags.egg-info/top_level.txt
sites_templatetags/__init__.py
sites_templatetags/models.py
sites_templatetags/templatetags/__init__.py
sites_templatetags/templatetags/sites.py