Metadata-Version: 1.0
Name: Django-Sites-Templatetags
Version: 0.0.2
Summary: Remove the ability to add or edit sites in Django's admin panel.
Home-page: https://github.com/RichardOfWard/django-sites-templatetags
Author: Richard Ward
Author-email: richard@richard.ward.name
License: MIT
Platform: UNKNOWN
